doclayout_yolo_slim/__init__.py
doclayout_yolo_slim/cfg/__init__.py
doclayout_yolo_slim/cfg/default.yaml
doclayout_yolo_slim/data/__intit__.py
doclayout_yolo_slim/data/augment.py
doclayout_yolo_slim/data/build.py
doclayout_yolo_slim/engine/__init__.py
doclayout_yolo_slim/engine/model.py
doclayout_yolo_slim/engine/predictor.py
doclayout_yolo_slim/engine/results.py
doclayout_yolo_slim/models/__init__.py
doclayout_yolo_slim/models/yolov10/__init__.py
doclayout_yolo_slim/models/yolov10/model.py
doclayout_yolo_slim/models/yolov10/predict.py
doclayout_yolo_slim/nn/__init__.py
doclayout_yolo_slim/nn/autobackend.py
doclayout_yolo_slim/nn/tasks.py
doclayout_yolo_slim/nn/modules/block.py
doclayout_yolo_slim/nn/modules/conv.py
doclayout_yolo_slim/nn/modules/g2l_crm.py
doclayout_yolo_slim/nn/modules/head.py
doclayout_yolo_slim/nn/modules/transformer.py
doclayout_yolo_slim/nn/modules/utils.py
doclayout_yolo_slim/nn/modules/modeling/__init__.py
doclayout_yolo_slim/utils/__init__.py
doclayout_yolo_slim/utils/checks.py
doclayout_yolo_slim/utils/downloads.py
doclayout_yolo_slim/utils/errors.py
doclayout_yolo_slim/utils/files.py
doclayout_yolo_slim/utils/instance.py
doclayout_yolo_slim/utils/loss.py
doclayout_yolo_slim/utils/ops.py
doclayout_yolo_slim/utils/patches.py
doclayout_yolo_slim/utils/tal.py
doclayout_yolo_slim/utils/torch_utils.py
doclayout_yolo_slim-0.1.0.dist-info/METADATA
doclayout_yolo_slim-0.1.0.dist-info/WHEEL
doclayout_yolo_slim-0.1.0.dist-info/licenses/LICENSE
doclayout_yolo_slim-0.1.0.dist-info/RECORD
