Metadata-Version: 2.4
Name: doclayout-yolo-slim
Version: 0.1.0
Summary: A simplified and faster implementation of doclayout-yolo for document layout inference
Author-email: Vladyslav Nalyvaiko <v.nalyvaiko@quextro.com>
License: AGPL-3.0
License-File: LICENSE
Keywords: analysis,computer-vision,document,layout,machine-learning,yolo
Classifier: Development Status :: 3 - Alpha
Classifier: Intended Audience :: Developers
Classifier: Intended Audience :: Science/Research
Classifier: License :: OSI Approved :: GNU Affero General Public License v3
Classifier: Operating System :: OS Independent
Classifier: Programming Language :: Python :: 3
Classifier: Programming Language :: Python :: 3.11
Classifier: Programming Language :: Python :: 3.12
Classifier: Topic :: Scientific/Engineering :: Artificial Intelligence
Classifier: Topic :: Software Development :: Libraries :: Python Modules
Requires-Python: >=3.11
Requires-Dist: matplotlib>=3.10.3
Requires-Dist: numpy>=2.3.1
Requires-Dist: opencv-python>=4.11.0.86
Requires-Dist: pandas>=2.3.0
Requires-Dist: py-cpuinfo>=9.0.0
Requires-Dist: pyyaml>=6.0.2
Requires-Dist: requests>=2.32.4
Requires-Dist: torch>=2.7.1
Requires-Dist: torchvision>=0.22.1
Requires-Dist: tqdm>=4.67.1
